[
  {
    "id": "159866_0_20260327131015",
    "code": "159866",
    "name": "日经ETF工银",
    "type": "BUY",
    "price": 1.368,
    "time": "2026-03-27 13:10:09",
    "status": "CLOSED",
    "reason": "突破后首次回踩 + RSI(72.3) + 量比(1.02x) + 回踩(0.15%) + 贴近MA5(0.01%)",
    "sell_price": 1.369,
    "sell_time": "2026-03-27 13:13:04",
    "profit": 0.001,
    "profit_pct": 0.07
  },
  {
    "id": "159866_SELL_20260327131309",
    "code": "159866",
    "name": "日经ETF工银",
    "type": "SELL",
    "price": 1.369,
    "time": "2026-03-27 13:13:04",
    "status": "CLOSED",
    "reason": "MA5 拐头止盈 (1.3686 < 1.3688)",
    "linked_buy_id": "159866_0_20260327131015",
    "buy_price": 1.368,
    "buy_time": "2026-03-27 13:10:09",
    "profit": 0.001,
    "profit_pct": 0.07
  }
]
