[
  {
    "time": "2026-04-16 09:30:00",
    "open": 1.234,
    "high": 1.234,
    "low": 1.234,
    "close": 1.234,
    "volume": 293657.0,
    "amount": 36237274.0,
    "code": "513050"
  },
  {
    "time": "2026-04-16 09:31:00",
    "open": 1.234,
    "high": 1.235,
    "low": 1.234,
    "close": 1.235,
    "volume": 808938.0,
    "amount": 99875280.0,
    "code": "513050"
  },
  {
    "time": "2026-04-16 09:32:00",
    "open": 1.235,
    "high": 1.235,
    "low": 1.235,
    "close": 1.235,
    "volume": 1253811.0,
    "amount": 154844216.0,
    "code": "513050"
  },
  {
    "time": "2026-04-16 09:33:00",
    "open": 1.235,
    "high": 1.235,
    "low": 1.233,
    "close": 1.233,
    "volume": 1451914.0,
    "amount": 179292489.54,
    "code": "513050"
  },
  {
    "time": "2026-04-16 09:34:00",
    "open": 1.233,
    "high": 1.235,
    "low": 1.233,
    "close": 1.235,
    "volume": 1859345.0,
    "amount": 229594036.55,
    "code": "513050"
  },
  {
    "time": "2026-04-16 09:35:00",
    "open": 1.235,
    "high": 1.235,
    "low": 1.233,
    "close": 1.233,
    "volume": 2141741.0,
    "amount": 264437167.55,
    "code": "513050"
  },
  {
    "time": "2026-04-16 09:36:00",
    "open": 1.233,
    "high": 1.234,
    "low": 1.233,
    "close": 1.234,
    "volume": 2367051.0,
    "amount": 292238047.55,
    "code": "513050"
  },
  {
    "time": "2026-04-16 09:37:00",
    "open": 1.234,
    "high": 1.235,
    "low": 1.234,
    "close": 1.235,
    "volume": 2627734.0,
    "amount": 324429548.55,
    "code": "513050"
  },
  {
    "time": "2026-04-16 09:38:00",
    "open": 1.235,
    "high": 1.236,
    "low": 1.235,
    "close": 1.236,
    "volume": 2960311.0,
    "amount": 365537820.55,
    "code": "513050"
  },
  {
    "time": "2026-04-16 09:39:00",
    "open": 1.236,
    "high": 1.237,
    "low": 1.236,
    "close": 1.237,
    "volume": 3065552.0,
    "amount": 378546709.55,
    "code": "513050"
  },
  {
    "time": "2026-04-16 09:40:00",
    "open": 1.237,
    "high": 1.238,
    "low": 1.237,
    "close": 1.238,
    "volume": 3269898.0,
    "amount": 403827883.54,
    "code": "513050"
  },
  {
    "time": "2026-04-16 09:41:00",
    "open": 1.238,
    "high": 1.238,
    "low": 1.238,
    "close": 1.238,
    "volume": 3597476.0,
    "amount": 444372135.41,
    "code": "513050"
  },
  {
    "time": "2026-04-16 09:42:00",
    "open": 1.238,
    "high": 1.238,
    "low": 1.238,
    "close": 1.238,
    "volume": 3942637.0,
    "amount": 487128560.42,
    "code": "513050"
  },
  {
    "time": "2026-04-16 09:43:00",
    "open": 1.238,
    "high": 1.239,
    "low": 1.238,
    "close": 1.239,
    "volume": 4041137.0,
    "amount": 499332000.42,
    "code": "513050"
  },
  {
    "time": "2026-04-16 09:44:00",
    "open": 1.239,
    "high": 1.241,
    "low": 1.239,
    "close": 1.241,
    "volume": 4373275.0,
    "amount": 540531506.43,
    "code": "513050"
  },
  {
    "time": "2026-04-16 09:45:00",
    "open": 1.241,
    "high": 1.241,
    "low": 1.241,
    "close": 1.241,
    "volume": 4600925.0,
    "amount": 568782357.43,
    "code": "513050"
  },
  {
    "time": "2026-04-16 09:46:00",
    "open": 1.241,
    "high": 1.241,
    "low": 1.239,
    "close": 1.239,
    "volume": 4801369.0,
    "amount": 593627537.44,
    "code": "513050"
  },
  {
    "time": "2026-04-16 09:47:00",
    "open": 1.239,
    "high": 1.24,
    "low": 1.239,
    "close": 1.24,
    "volume": 5021429.0,
    "amount": 620900102.44,
    "code": "513050"
  },
  {
    "time": "2026-04-16 09:48:00",
    "open": 1.24,
    "high": 1.24,
    "low": 1.239,
    "close": 1.239,
    "volume": 5102948.0,
    "amount": 631009103.44,
    "code": "513050"
  },
  {
    "time": "2026-04-16 09:49:00",
    "open": 1.239,
    "high": 1.239,
    "low": 1.239,
    "close": 1.239,
    "volume": 5186378.0,
    "amount": 641346398.44,
    "code": "513050"
  },
  {
    "time": "2026-04-16 09:50:00",
    "open": 1.239,
    "high": 1.24,
    "low": 1.239,
    "close": 1.24,
    "volume": 5245678.0,
    "amount": 648693754.44,
    "code": "513050"
  },
  {
    "time": "2026-04-16 09:51:00",
    "open": 1.24,
    "high": 1.24,
    "low": 1.239,
    "close": 1.239,
    "volume": 5353041.0,
    "amount": 661995571.44,
    "code": "513050"
  },
  {
    "time": "2026-04-16 09:52:00",
    "open": 1.239,
    "high": 1.239,
    "low": 1.238,
    "close": 1.238,
    "volume": 5418138.0,
    "amount": 670059274.44,
    "code": "513050"
  },
  {
    "time": "2026-04-16 09:53:00",
    "open": 1.238,
    "high": 1.238,
    "low": 1.237,
    "close": 1.237,
    "volume": 5507919.0,
    "amount": 681172175.44,
    "code": "513050"
  },
  {
    "time": "2026-04-16 09:54:00",
    "open": 1.237,
    "high": 1.239,
    "low": 1.237,
    "close": 1.239,
    "volume": 5595965.0,
    "amount": 692074252.44,
    "code": "513050"
  },
  {
    "time": "2026-04-16 09:55:00",
    "open": 1.239,
    "high": 1.239,
    "low": 1.237,
    "close": 1.237,
    "volume": 5710212.0,
    "amount": 706218044.05,
    "code": "513050"
  },
  {
    "time": "2026-04-16 09:56:00",
    "open": 1.237,
    "high": 1.237,
    "low": 1.236,
    "close": 1.236,
    "volume": 5825623.0,
    "amount": 720494426.45,
    "code": "513050"
  },
  {
    "time": "2026-04-16 09:57:00",
    "open": 1.236,
    "high": 1.238,
    "low": 1.236,
    "close": 1.238,
    "volume": 5933791.0,
    "amount": 733879705.45,
    "code": "513050"
  },
  {
    "time": "2026-04-16 09:58:00",
    "open": 1.238,
    "high": 1.238,
    "low": 1.238,
    "close": 1.238,
    "volume": 5960091.0,
    "amount": 737136852.45,
    "code": "513050"
  },
  {
    "time": "2026-04-16 09:59:00",
    "open": 1.238,
    "high": 1.238,
    "low": 1.238,
    "close": 1.238,
    "volume": 6149229.0,
    "amount": 760564639.45,
    "code": "513050"
  },
  {
    "time": "2026-04-16 10:00:00",
    "open": 1.238,
    "high": 1.238,
    "low": 1.238,
    "close": 1.238,
    "volume": 6164731.0,
    "amount": 762482493.45,
    "code": "513050"
  },
  {
    "time": "2026-04-16 10:01:00",
    "open": 1.238,
    "high": 1.238,
    "low": 1.238,
    "close": 1.238,
    "volume": 6250244.0,
    "amount": 773069442.45,
    "code": "513050"
  },
  {
    "time": "2026-04-16 10:02:00",
    "open": 1.238,
    "high": 1.238,
    "low": 1.238,
    "close": 1.238,
    "volume": 6441847.0,
    "amount": 796797511.45,
    "code": "513050"
  },
  {
    "time": "2026-04-16 10:03:00",
    "open": 1.238,
    "high": 1.238,
    "low": 1.238,
    "close": 1.238,
    "volume": 6499417.0,
    "amount": 803924628.45,
    "code": "513050"
  },
  {
    "time": "2026-04-16 10:04:00",
    "open": 1.238,
    "high": 1.238,
    "low": 1.238,
    "close": 1.238,
    "volume": 6535424.0,
    "amount": 808382334.45,
    "code": "513050"
  },
  {
    "time": "2026-04-16 10:05:00",
    "open": 1.238,
    "high": 1.239,
    "low": 1.238,
    "close": 1.239,
    "volume": 6639846.0,
    "amount": 821319411.45,
    "code": "513050"
  },
  {
    "time": "2026-04-16 10:06:00",
    "open": 1.239,
    "high": 1.24,
    "low": 1.239,
    "close": 1.24,
    "volume": 6658860.0,
    "amount": 823676568.45,
    "code": "513050"
  },
  {
    "time": "2026-04-16 10:07:00",
    "open": 1.24,
    "high": 1.24,
    "low": 1.24,
    "close": 1.24,
    "volume": 6674202.0,
    "amount": 825578128.45,
    "code": "513050"
  },
  {
    "time": "2026-04-16 10:08:00",
    "open": 1.24,
    "high": 1.24,
    "low": 1.239,
    "close": 1.239,
    "volume": 6710736.0,
    "amount": 830104361.45,
    "code": "513050"
  },
  {
    "time": "2026-04-16 10:09:00",
    "open": 1.239,
    "high": 1.24,
    "low": 1.239,
    "close": 1.24,
    "volume": 6790070.0,
    "amount": 839934267.45,
    "code": "513050"
  },
  {
    "time": "2026-04-16 10:10:00",
    "open": 1.24,
    "high": 1.24,
    "low": 1.24,
    "close": 1.24,
    "volume": 6815480.0,
    "amount": 843083386.45,
    "code": "513050"
  },
  {
    "time": "2026-04-16 10:11:00",
    "open": 1.24,
    "high": 1.24,
    "low": 1.239,
    "close": 1.239,
    "volume": 6838427.0,
    "amount": 845927543.45,
    "code": "513050"
  },
  {
    "time": "2026-04-16 10:12:00",
    "open": 1.239,
    "high": 1.239,
    "low": 1.239,
    "close": 1.239,
    "volume": 6947376.0,
    "amount": 859426545.45,
    "code": "513050"
  },
  {
    "time": "2026-04-16 10:13:00",
    "open": 1.239,
    "high": 1.239,
    "low": 1.238,
    "close": 1.238,
    "volume": 6975289.0,
    "amount": 862884464.45,
    "code": "513050"
  },
  {
    "time": "2026-04-16 10:14:00",
    "open": 1.238,
    "high": 1.238,
    "low": 1.238,
    "close": 1.238,
    "volume": 7006393.0,
    "amount": 866735341.45,
    "code": "513050"
  },
  {
    "time": "2026-04-16 10:15:00",
    "open": 1.238,
    "high": 1.238,
    "low": 1.237,
    "close": 1.237,
    "volume": 7115977.0,
    "amount": 880289982.45,
    "code": "513050"
  },
  {
    "time": "2026-04-16 10:16:00",
    "open": 1.237,
    "high": 1.237,
    "low": 1.237,
    "close": 1.237,
    "volume": 7153436.0,
    "amount": 884923691.45,
    "code": "513050"
  },
  {
    "time": "2026-04-16 10:17:00",
    "open": 1.237,
    "high": 1.237,
    "low": 1.237,
    "close": 1.237,
    "volume": 7168052.0,
    "amount": 886731735.45,
    "code": "513050"
  },
  {
    "time": "2026-04-16 10:18:00",
    "open": 1.237,
    "high": 1.24,
    "low": 1.237,
    "close": 1.24,
    "volume": 7425065.0,
    "amount": 918577029.45,
    "code": "513050"
  },
  {
    "time": "2026-04-16 10:19:00",
    "open": 1.24,
    "high": 1.24,
    "low": 1.239,
    "close": 1.239,
    "volume": 7629160.0,
    "amount": 943885289.46,
    "code": "513050"
  },
  {
    "time": "2026-04-16 10:20:00",
    "open": 1.239,
    "high": 1.239,
    "low": 1.239,
    "close": 1.239,
    "volume": 7679770.0,
    "amount": 950156068.46,
    "code": "513050"
  },
  {
    "time": "2026-04-16 10:21:00",
    "open": 1.239,
    "high": 1.239,
    "low": 1.239,
    "close": 1.239,
    "volume": 7719967.0,
    "amount": 955136354.46,
    "code": "513050"
  },
  {
    "time": "2026-04-16 10:22:00",
    "open": 1.239,
    "high": 1.239,
    "low": 1.239,
    "close": 1.239,
    "volume": 7757924.0,
    "amount": 959838793.46,
    "code": "513050"
  },
  {
    "time": "2026-04-16 10:23:00",
    "open": 1.239,
    "high": 1.239,
    "low": 1.238,
    "close": 1.238,
    "volume": 7869321.0,
    "amount": 973632826.46,
    "code": "513050"
  },
  {
    "time": "2026-04-16 10:24:00",
    "open": 1.238,
    "high": 1.238,
    "low": 1.238,
    "close": 1.238,
    "volume": 7888215.0,
    "amount": 975971728.46,
    "code": "513050"
  },
  {
    "time": "2026-04-16 10:25:00",
    "open": 1.238,
    "high": 1.238,
    "low": 1.237,
    "close": 1.237,
    "volume": 7907641.0,
    "amount": 978376040.46,
    "code": "513050"
  },
  {
    "time": "2026-04-16 10:26:00",
    "open": 1.237,
    "high": 1.24,
    "low": 1.237,
    "close": 1.24,
    "volume": 7949750.0,
    "amount": 983591743.46,
    "code": "513050"
  },
  {
    "time": "2026-04-16 10:27:00",
    "open": 1.24,
    "high": 1.24,
    "low": 1.239,
    "close": 1.239,
    "volume": 7975456.0,
    "amount": 986776906.46,
    "code": "513050"
  },
  {
    "time": "2026-04-16 10:28:00",
    "open": 1.239,
    "high": 1.24,
    "low": 1.239,
    "close": 1.24,
    "volume": 8156877.0,
    "amount": 1009272791.46,
    "code": "513050"
  },
  {
    "time": "2026-04-16 10:29:00",
    "open": 1.24,
    "high": 1.242,
    "low": 1.24,
    "close": 1.242,
    "volume": 8329595.0,
    "amount": 1030706726.46,
    "code": "513050"
  },
  {
    "time": "2026-04-16 10:30:00",
    "open": 1.242,
    "high": 1.242,
    "low": 1.241,
    "close": 1.241,
    "volume": 8431659.0,
    "amount": 1043372904.46,
    "code": "513050"
  },
  {
    "time": "2026-04-16 10:31:00",
    "open": 1.241,
    "high": 1.243,
    "low": 1.241,
    "close": 1.243,
    "volume": 8766985.0,
    "amount": 1085036317.47,
    "code": "513050"
  },
  {
    "time": "2026-04-16 10:32:00",
    "open": 1.243,
    "high": 1.244,
    "low": 1.243,
    "close": 1.244,
    "volume": 8883572.0,
    "amount": 1099538265.47,
    "code": "513050"
  },
  {
    "time": "2026-04-16 10:33:00",
    "open": 1.244,
    "high": 1.245,
    "low": 1.244,
    "close": 1.245,
    "volume": 9223050.0,
    "amount": 1141786309.47,
    "code": "513050"
  },
  {
    "time": "2026-04-16 10:34:00",
    "open": 1.245,
    "high": 1.245,
    "low": 1.243,
    "close": 1.243,
    "volume": 9315271.0,
    "amount": 1153264255.47,
    "code": "513050"
  },
  {
    "time": "2026-04-16 10:35:00",
    "open": 1.243,
    "high": 1.244,
    "low": 1.243,
    "close": 1.244,
    "volume": 9390211.0,
    "amount": 1162585696.48,
    "code": "513050"
  },
  {
    "time": "2026-04-16 10:36:00",
    "open": 1.244,
    "high": 1.244,
    "low": 1.243,
    "close": 1.243,
    "volume": 9448431.0,
    "amount": 1169828059.48,
    "code": "513050"
  },
  {
    "time": "2026-04-16 10:37:00",
    "open": 1.243,
    "high": 1.245,
    "low": 1.243,
    "close": 1.245,
    "volume": 9537127.0,
    "amount": 1180869467.48,
    "code": "513050"
  },
  {
    "time": "2026-04-16 10:38:00",
    "open": 1.245,
    "high": 1.246,
    "low": 1.245,
    "close": 1.246,
    "volume": 9619264.0,
    "amount": 1191098698.48,
    "code": "513050"
  },
  {
    "time": "2026-04-16 10:39:00",
    "open": 1.246,
    "high": 1.246,
    "low": 1.246,
    "close": 1.246,
    "volume": 9667283.0,
    "amount": 1197080558.48,
    "code": "513050"
  },
  {
    "time": "2026-04-16 10:40:00",
    "open": 1.246,
    "high": 1.246,
    "low": 1.246,
    "close": 1.246,
    "volume": 9764644.0,
    "amount": 1209211213.48,
    "code": "513050"
  },
  {
    "time": "2026-04-16 10:41:00",
    "open": 1.246,
    "high": 1.247,
    "low": 1.246,
    "close": 1.247,
    "volume": 9849917.0,
    "amount": 1219838711.48,
    "code": "513050"
  },
  {
    "time": "2026-04-16 10:42:00",
    "open": 1.247,
    "high": 1.247,
    "low": 1.246,
    "close": 1.246,
    "volume": 9924457.0,
    "amount": 1229125916.49,
    "code": "513050"
  },
  {
    "time": "2026-04-16 10:43:00",
    "open": 1.246,
    "high": 1.246,
    "low": 1.246,
    "close": 1.246,
    "volume": 9978297.0,
    "amount": 1235835732.49,
    "code": "513050"
  },
  {
    "time": "2026-04-16 10:44:00",
    "open": 1.246,
    "high": 1.246,
    "low": 1.244,
    "close": 1.244,
    "volume": 10037323.0,
    "amount": 1243185005.49,
    "code": "513050"
  },
  {
    "time": "2026-04-16 10:45:00",
    "open": 1.244,
    "high": 1.244,
    "low": 1.244,
    "close": 1.244,
    "volume": 10127813.0,
    "amount": 1254441367.49,
    "code": "513050"
  },
  {
    "time": "2026-04-16 10:46:00",
    "open": 1.244,
    "high": 1.245,
    "low": 1.244,
    "close": 1.245,
    "volume": 10217396.0,
    "amount": 1265590402.02,
    "code": "513050"
  },
  {
    "time": "2026-04-16 10:47:00",
    "open": 1.245,
    "high": 1.245,
    "low": 1.243,
    "close": 1.243,
    "volume": 10243074.0,
    "amount": 1268783990.02,
    "code": "513050"
  },
  {
    "time": "2026-04-16 10:48:00",
    "open": 1.243,
    "high": 1.243,
    "low": 1.242,
    "close": 1.242,
    "volume": 10301696.0,
    "amount": 1276068590.03,
    "code": "513050"
  },
  {
    "time": "2026-04-16 10:49:00",
    "open": 1.242,
    "high": 1.243,
    "low": 1.242,
    "close": 1.243,
    "volume": 10341183.0,
    "amount": 1280977517.03,
    "code": "513050"
  },
  {
    "time": "2026-04-16 10:50:00",
    "open": 1.243,
    "high": 1.244,
    "low": 1.243,
    "close": 1.244,
    "volume": 10375330.0,
    "amount": 1285225224.03,
    "code": "513050"
  },
  {
    "time": "2026-04-16 10:51:00",
    "open": 1.244,
    "high": 1.244,
    "low": 1.243,
    "close": 1.243,
    "volume": 10389547.0,
    "amount": 1286992698.03,
    "code": "513050"
  },
  {
    "time": "2026-04-16 10:52:00",
    "open": 1.243,
    "high": 1.243,
    "low": 1.243,
    "close": 1.243,
    "volume": 10394195.0,
    "amount": 1287570748.03,
    "code": "513050"
  },
  {
    "time": "2026-04-16 10:53:00",
    "open": 1.243,
    "high": 1.244,
    "low": 1.243,
    "close": 1.244,
    "volume": 10469217.0,
    "amount": 1296896067.03,
    "code": "513050"
  },
  {
    "time": "2026-04-16 10:54:00",
    "open": 1.244,
    "high": 1.244,
    "low": 1.243,
    "close": 1.243,
    "volume": 10517257.0,
    "amount": 1302867507.03,
    "code": "513050"
  },
  {
    "time": "2026-04-16 10:55:00",
    "open": 1.243,
    "high": 1.244,
    "low": 1.243,
    "close": 1.244,
    "volume": 10573109.0,
    "amount": 1309815032.03,
    "code": "513050"
  },
  {
    "time": "2026-04-16 10:56:00",
    "open": 1.244,
    "high": 1.246,
    "low": 1.244,
    "close": 1.246,
    "volume": 10645097.0,
    "amount": 1318780044.03,
    "code": "513050"
  },
  {
    "time": "2026-04-16 10:57:00",
    "open": 1.246,
    "high": 1.247,
    "low": 1.246,
    "close": 1.247,
    "volume": 10811496.0,
    "amount": 1339525353.04,
    "code": "513050"
  },
  {
    "time": "2026-04-16 10:58:00",
    "open": 1.247,
    "high": 1.247,
    "low": 1.246,
    "close": 1.246,
    "volume": 10867964.0,
    "amount": 1346566032.04,
    "code": "513050"
  },
  {
    "time": "2026-04-16 10:59:00",
    "open": 1.246,
    "high": 1.246,
    "low": 1.246,
    "close": 1.246,
    "volume": 10915874.0,
    "amount": 1352535879.04,
    "code": "513050"
  },
  {
    "time": "2026-04-16 11:00:00",
    "open": 1.246,
    "high": 1.246,
    "low": 1.246,
    "close": 1.246,
    "volume": 10940957.0,
    "amount": 1355661354.04,
    "code": "513050"
  },
  {
    "time": "2026-04-16 11:01:00",
    "open": 1.246,
    "high": 1.246,
    "low": 1.246,
    "close": 1.246,
    "volume": 10950841.0,
    "amount": 1356892492.04,
    "code": "513050"
  },
  {
    "time": "2026-04-16 11:02:00",
    "open": 1.246,
    "high": 1.246,
    "low": 1.245,
    "close": 1.245,
    "volume": 11005973.0,
    "amount": 1363760921.04,
    "code": "513050"
  },
  {
    "time": "2026-04-16 11:03:00",
    "open": 1.245,
    "high": 1.246,
    "low": 1.245,
    "close": 1.246,
    "volume": 11099546.0,
    "amount": 1375420636.05,
    "code": "513050"
  },
  {
    "time": "2026-04-16 11:04:00",
    "open": 1.246,
    "high": 1.246,
    "low": 1.246,
    "close": 1.246,
    "volume": 11114990.0,
    "amount": 1377344680.05,
    "code": "513050"
  },
  {
    "time": "2026-04-16 11:05:00",
    "open": 1.246,
    "high": 1.247,
    "low": 1.246,
    "close": 1.247,
    "volume": 11152658.0,
    "amount": 1382038330.05,
    "code": "513050"
  },
  {
    "time": "2026-04-16 11:06:00",
    "open": 1.247,
    "high": 1.247,
    "low": 1.246,
    "close": 1.246,
    "volume": 11173757.0,
    "amount": 1384669342.05,
    "code": "513050"
  },
  {
    "time": "2026-04-16 11:07:00",
    "open": 1.246,
    "high": 1.248,
    "low": 1.246,
    "close": 1.248,
    "volume": 11263147.0,
    "amount": 1395816631.05,
    "code": "513050"
  },
  {
    "time": "2026-04-16 11:08:00",
    "open": 1.248,
    "high": 1.248,
    "low": 1.248,
    "close": 1.248,
    "volume": 11447562.0,
    "amount": 1418832382.06,
    "code": "513050"
  },
  {
    "time": "2026-04-16 11:09:00",
    "open": 1.248,
    "high": 1.248,
    "low": 1.247,
    "close": 1.247,
    "volume": 11473002.0,
    "amount": 1422007051.06,
    "code": "513050"
  },
  {
    "time": "2026-04-16 11:10:00",
    "open": 1.247,
    "high": 1.248,
    "low": 1.247,
    "close": 1.248,
    "volume": 11539317.0,
    "amount": 1430283632.06,
    "code": "513050"
  },
  {
    "time": "2026-04-16 11:11:00",
    "open": 1.248,
    "high": 1.248,
    "low": 1.247,
    "close": 1.247,
    "volume": 11564248.0,
    "amount": 1433395491.06,
    "code": "513050"
  },
  {
    "time": "2026-04-16 11:12:00",
    "open": 1.247,
    "high": 1.247,
    "low": 1.247,
    "close": 1.247,
    "volume": 11586252.0,
    "amount": 1436139538.06,
    "code": "513050"
  },
  {
    "time": "2026-04-16 11:13:00",
    "open": 1.247,
    "high": 1.247,
    "low": 1.247,
    "close": 1.247,
    "volume": 11717919.0,
    "amount": 1452551335.06,
    "code": "513050"
  },
  {
    "time": "2026-04-16 11:14:00",
    "open": 1.247,
    "high": 1.247,
    "low": 1.247,
    "close": 1.247,
    "volume": 11747155.0,
    "amount": 1456196800.06,
    "code": "513050"
  },
  {
    "time": "2026-04-16 11:15:00",
    "open": 1.247,
    "high": 1.247,
    "low": 1.247,
    "close": 1.247,
    "volume": 11775230.0,
    "amount": 1459697461.06,
    "code": "513050"
  },
  {
    "time": "2026-04-16 11:16:00",
    "open": 1.247,
    "high": 1.247,
    "low": 1.247,
    "close": 1.247,
    "volume": 11819561.0,
    "amount": 1465225696.07,
    "code": "513050"
  },
  {
    "time": "2026-04-16 11:17:00",
    "open": 1.247,
    "high": 1.247,
    "low": 1.247,
    "close": 1.247,
    "volume": 11834474.0,
    "amount": 1467085382.07,
    "code": "513050"
  },
  {
    "time": "2026-04-16 11:18:00",
    "open": 1.247,
    "high": 1.247,
    "low": 1.247,
    "close": 1.247,
    "volume": 11842750.0,
    "amount": 1468117809.07,
    "code": "513050"
  },
  {
    "time": "2026-04-16 11:19:00",
    "open": 1.247,
    "high": 1.247,
    "low": 1.247,
    "close": 1.247,
    "volume": 11847267.0,
    "amount": 1468681300.07,
    "code": "513050"
  },
  {
    "time": "2026-04-16 11:20:00",
    "open": 1.247,
    "high": 1.247,
    "low": 1.247,
    "close": 1.247,
    "volume": 11855219.0,
    "amount": 1469673097.07,
    "code": "513050"
  },
  {
    "time": "2026-04-16 11:21:00",
    "open": 1.247,
    "high": 1.248,
    "low": 1.247,
    "close": 1.248,
    "volume": 11949048.0,
    "amount": 1481382514.07,
    "code": "513050"
  },
  {
    "time": "2026-04-16 11:22:00",
    "open": 1.248,
    "high": 1.25,
    "low": 1.248,
    "close": 1.25,
    "volume": 12299515.0,
    "amount": 1525181631.08,
    "code": "513050"
  },
  {
    "time": "2026-04-16 11:23:00",
    "open": 1.25,
    "high": 1.25,
    "low": 1.25,
    "close": 1.25,
    "volume": 12382195.0,
    "amount": 1535516311.08,
    "code": "513050"
  },
  {
    "time": "2026-04-16 11:24:00",
    "open": 1.25,
    "high": 1.25,
    "low": 1.249,
    "close": 1.249,
    "volume": 12411759.0,
    "amount": 1539211671.09,
    "code": "513050"
  },
  {
    "time": "2026-04-16 11:25:00",
    "open": 1.249,
    "high": 1.25,
    "low": 1.249,
    "close": 1.25,
    "volume": 12465479.0,
    "amount": 1545926663.09,
    "code": "513050"
  },
  {
    "time": "2026-04-16 11:26:00",
    "open": 1.25,
    "high": 1.25,
    "low": 1.25,
    "close": 1.25,
    "volume": 12503240.0,
    "amount": 1550649565.09,
    "code": "513050"
  },
  {
    "time": "2026-04-16 11:27:00",
    "open": 1.25,
    "high": 1.25,
    "low": 1.25,
    "close": 1.25,
    "volume": 12520601.0,
    "amount": 1552819914.09,
    "code": "513050"
  },
  {
    "time": "2026-04-16 11:28:00",
    "open": 1.25,
    "high": 1.25,
    "low": 1.25,
    "close": 1.25,
    "volume": 12542607.0,
    "amount": 1555571811.09,
    "code": "513050"
  },
  {
    "time": "2026-04-16 11:29:00",
    "open": 1.25,
    "high": 1.25,
    "low": 1.25,
    "close": 1.25,
    "volume": 12570879.0,
    "amount": 1559107954.09,
    "code": "513050"
  },
  {
    "time": "2026-04-16 11:30:00",
    "open": 1.25,
    "high": 1.252,
    "low": 1.25,
    "close": 1.252,
    "volume": 12736601.0,
    "amount": 1579838244.1,
    "code": "513050"
  },
  {
    "time": "2026-04-16 13:00:00",
    "open": 1.252,
    "high": 1.252,
    "low": 1.252,
    "close": 1.252,
    "volume": 12736601.0,
    "amount": 1579838244.1,
    "code": "513050"
  },
  {
    "time": "2026-04-16 13:01:00",
    "open": 1.252,
    "high": 1.252,
    "low": 1.252,
    "close": 1.252,
    "volume": 13118458.0,
    "amount": 1627646305.11,
    "code": "513050"
  },
  {
    "time": "2026-04-16 13:02:00",
    "open": 1.252,
    "high": 1.253,
    "low": 1.252,
    "close": 1.253,
    "volume": 13276458.0,
    "amount": 1647441816.12,
    "code": "513050"
  },
  {
    "time": "2026-04-16 13:03:00",
    "open": 1.253,
    "high": 1.253,
    "low": 1.251,
    "close": 1.251,
    "volume": 13381915.0,
    "amount": 1660645528.12,
    "code": "513050"
  },
  {
    "time": "2026-04-16 13:04:00",
    "open": 1.251,
    "high": 1.252,
    "low": 1.251,
    "close": 1.252,
    "volume": 13473244.0,
    "amount": 1672078749.12,
    "code": "513050"
  },
  {
    "time": "2026-04-16 13:05:00",
    "open": 1.252,
    "high": 1.252,
    "low": 1.25,
    "close": 1.25,
    "volume": 13631282.0,
    "amount": 1691842238.13,
    "code": "513050"
  },
  {
    "time": "2026-04-16 13:06:00",
    "open": 1.25,
    "high": 1.25,
    "low": 1.248,
    "close": 1.248,
    "volume": 13805511.0,
    "amount": 1713603532.13,
    "code": "513050"
  },
  {
    "time": "2026-04-16 13:07:00",
    "open": 1.248,
    "high": 1.249,
    "low": 1.248,
    "close": 1.249,
    "volume": 13902499.0,
    "amount": 1725716922.13,
    "code": "513050"
  },
  {
    "time": "2026-04-16 13:08:00",
    "open": 1.249,
    "high": 1.249,
    "low": 1.248,
    "close": 1.248,
    "volume": 14041583.0,
    "amount": 1743086009.14,
    "code": "513050"
  },
  {
    "time": "2026-04-16 13:09:00",
    "open": 1.248,
    "high": 1.248,
    "low": 1.247,
    "close": 1.247,
    "volume": 14139051.0,
    "amount": 1755243654.14,
    "code": "513050"
  },
  {
    "time": "2026-04-16 13:10:00",
    "open": 1.247,
    "high": 1.247,
    "low": 1.247,
    "close": 1.247,
    "volume": 14241915.0,
    "amount": 1768067553.14,
    "code": "513050"
  },
  {
    "time": "2026-04-16 13:11:00",
    "open": 1.247,
    "high": 1.248,
    "low": 1.247,
    "close": 1.248,
    "volume": 14338990.0,
    "amount": 1780181685.14,
    "code": "513050"
  },
  {
    "time": "2026-04-16 13:12:00",
    "open": 1.248,
    "high": 1.248,
    "low": 1.248,
    "close": 1.248,
    "volume": 14432551.0,
    "amount": 1791863153.14,
    "code": "513050"
  },
  {
    "time": "2026-04-16 13:13:00",
    "open": 1.248,
    "high": 1.248,
    "low": 1.248,
    "close": 1.248,
    "volume": 14442334.0,
    "amount": 1793084286.14,
    "code": "513050"
  },
  {
    "time": "2026-04-16 13:14:00",
    "open": 1.248,
    "high": 1.249,
    "low": 1.248,
    "close": 1.249,
    "volume": 14513470.0,
    "amount": 1801968510.15,
    "code": "513050"
  },
  {
    "time": "2026-04-16 13:15:00",
    "open": 1.249,
    "high": 1.249,
    "low": 1.249,
    "close": 1.249,
    "volume": 14581910.0,
    "amount": 1810517239.15,
    "code": "513050"
  },
  {
    "time": "2026-04-16 13:16:00",
    "open": 1.249,
    "high": 1.249,
    "low": 1.248,
    "close": 1.248,
    "volume": 14677120.0,
    "amount": 1822408807.15,
    "code": "513050"
  },
  {
    "time": "2026-04-16 13:17:00",
    "open": 1.248,
    "high": 1.25,
    "low": 1.248,
    "close": 1.25,
    "volume": 14764014.0,
    "amount": 1833268769.15,
    "code": "513050"
  },
  {
    "time": "2026-04-16 13:18:00",
    "open": 1.25,
    "high": 1.251,
    "low": 1.25,
    "close": 1.251,
    "volume": 14835393.0,
    "amount": 1842198083.15,
    "code": "513050"
  },
  {
    "time": "2026-04-16 13:19:00",
    "open": 1.251,
    "high": 1.251,
    "low": 1.251,
    "close": 1.251,
    "volume": 14865980.0,
    "amount": 1846025276.15,
    "code": "513050"
  },
  {
    "time": "2026-04-16 13:20:00",
    "open": 1.251,
    "high": 1.252,
    "low": 1.251,
    "close": 1.252,
    "volume": 14939589.0,
    "amount": 1855240927.16,
    "code": "513050"
  },
  {
    "time": "2026-04-16 13:21:00",
    "open": 1.252,
    "high": 1.252,
    "low": 1.252,
    "close": 1.252,
    "volume": 14951420.0,
    "amount": 1856723016.16,
    "code": "513050"
  },
  {
    "time": "2026-04-16 13:22:00",
    "open": 1.252,
    "high": 1.253,
    "low": 1.252,
    "close": 1.253,
    "volume": 14968910.0,
    "amount": 1858914212.16,
    "code": "513050"
  },
  {
    "time": "2026-04-16 13:23:00",
    "open": 1.253,
    "high": 1.253,
    "low": 1.252,
    "close": 1.252,
    "volume": 15039116.0,
    "amount": 1867704195.16,
    "code": "513050"
  },
  {
    "time": "2026-04-16 13:24:00",
    "open": 1.252,
    "high": 1.252,
    "low": 1.251,
    "close": 1.251,
    "volume": 15174221.0,
    "amount": 1884619412.16,
    "code": "513050"
  },
  {
    "time": "2026-04-16 13:25:00",
    "open": 1.251,
    "high": 1.251,
    "low": 1.251,
    "close": 1.251,
    "volume": 15233919.0,
    "amount": 1892092344.17,
    "code": "513050"
  },
  {
    "time": "2026-04-16 13:26:00",
    "open": 1.251,
    "high": 1.252,
    "low": 1.251,
    "close": 1.252,
    "volume": 15272013.0,
    "amount": 1896861508.41,
    "code": "513050"
  },
  {
    "time": "2026-04-16 13:27:00",
    "open": 1.252,
    "high": 1.252,
    "low": 1.252,
    "close": 1.252,
    "volume": 15296534.0,
    "amount": 1899931581.41,
    "code": "513050"
  },
  {
    "time": "2026-04-16 13:28:00",
    "open": 1.252,
    "high": 1.253,
    "low": 1.252,
    "close": 1.253,
    "volume": 15462336.0,
    "amount": 1920704704.41,
    "code": "513050"
  },
  {
    "time": "2026-04-16 13:29:00",
    "open": 1.253,
    "high": 1.253,
    "low": 1.253,
    "close": 1.253,
    "volume": 15529511.0,
    "amount": 1929121700.42,
    "code": "513050"
  },
  {
    "time": "2026-04-16 13:30:00",
    "open": 1.253,
    "high": 1.254,
    "low": 1.253,
    "close": 1.254,
    "volume": 15608197.0,
    "amount": 1938988296.42,
    "code": "513050"
  },
  {
    "time": "2026-04-16 13:31:00",
    "open": 1.254,
    "high": 1.254,
    "low": 1.254,
    "close": 1.254,
    "volume": 15716815.0,
    "amount": 1952609822.42,
    "code": "513050"
  },
  {
    "time": "2026-04-16 13:32:00",
    "open": 1.254,
    "high": 1.254,
    "low": 1.254,
    "close": 1.254,
    "volume": 15750304.0,
    "amount": 1956809065.42,
    "code": "513050"
  },
  {
    "time": "2026-04-16 13:33:00",
    "open": 1.254,
    "high": 1.254,
    "low": 1.253,
    "close": 1.253,
    "volume": 15956492.0,
    "amount": 1982644131.43,
    "code": "513050"
  },
  {
    "time": "2026-04-16 13:34:00",
    "open": 1.253,
    "high": 1.254,
    "low": 1.253,
    "close": 1.254,
    "volume": 16007290.0,
    "amount": 1989008816.43,
    "code": "513050"
  },
  {
    "time": "2026-04-16 13:35:00",
    "open": 1.254,
    "high": 1.254,
    "low": 1.252,
    "close": 1.252,
    "volume": 16036739.0,
    "amount": 1992698453.43,
    "code": "513050"
  },
  {
    "time": "2026-04-16 13:36:00",
    "open": 1.252,
    "high": 1.252,
    "low": 1.252,
    "close": 1.252,
    "volume": 16052932.0,
    "amount": 1994725976.43,
    "code": "513050"
  },
  {
    "time": "2026-04-16 13:37:00",
    "open": 1.252,
    "high": 1.252,
    "low": 1.252,
    "close": 1.252,
    "volume": 16071095.0,
    "amount": 1997000907.43,
    "code": "513050"
  },
  {
    "time": "2026-04-16 13:38:00",
    "open": 1.252,
    "high": 1.252,
    "low": 1.251,
    "close": 1.251,
    "volume": 16187621.0,
    "amount": 2011591133.43,
    "code": "513050"
  },
  {
    "time": "2026-04-16 13:39:00",
    "open": 1.251,
    "high": 1.252,
    "low": 1.251,
    "close": 1.252,
    "volume": 16237630.0,
    "amount": 2017852130.44,
    "code": "513050"
  },
  {
    "time": "2026-04-16 13:40:00",
    "open": 1.252,
    "high": 1.252,
    "low": 1.251,
    "close": 1.251,
    "volume": 16291139.0,
    "amount": 2024551635.44,
    "code": "513050"
  },
  {
    "time": "2026-04-16 13:41:00",
    "open": 1.251,
    "high": 1.251,
    "low": 1.251,
    "close": 1.251,
    "volume": 16318078.0,
    "amount": 2027924321.44,
    "code": "513050"
  },
  {
    "time": "2026-04-16 13:42:00",
    "open": 1.251,
    "high": 1.252,
    "low": 1.251,
    "close": 1.252,
    "volume": 16326484.0,
    "amount": 2028976063.44,
    "code": "513050"
  },
  {
    "time": "2026-04-16 13:43:00",
    "open": 1.252,
    "high": 1.252,
    "low": 1.251,
    "close": 1.251,
    "volume": 16343824.0,
    "amount": 2031145936.44,
    "code": "513050"
  },
  {
    "time": "2026-04-16 13:44:00",
    "open": 1.251,
    "high": 1.251,
    "low": 1.25,
    "close": 1.25,
    "volume": 16451023.0,
    "amount": 2044553738.2,
    "code": "513050"
  },
  {
    "time": "2026-04-16 13:45:00",
    "open": 1.25,
    "high": 1.25,
    "low": 1.25,
    "close": 1.25,
    "volume": 16483280.0,
    "amount": 2048586033.2,
    "code": "513050"
  },
  {
    "time": "2026-04-16 13:46:00",
    "open": 1.25,
    "high": 1.251,
    "low": 1.25,
    "close": 1.251,
    "volume": 16547991.0,
    "amount": 2056680126.2,
    "code": "513050"
  },
  {
    "time": "2026-04-16 13:47:00",
    "open": 1.251,
    "high": 1.252,
    "low": 1.251,
    "close": 1.252,
    "volume": 16561162.0,
    "amount": 2058328054.2,
    "code": "513050"
  },
  {
    "time": "2026-04-16 13:48:00",
    "open": 1.252,
    "high": 1.252,
    "low": 1.251,
    "close": 1.251,
    "volume": 16581634.0,
    "amount": 2060890852.2,
    "code": "513050"
  },
  {
    "time": "2026-04-16 13:49:00",
    "open": 1.251,
    "high": 1.252,
    "low": 1.251,
    "close": 1.252,
    "volume": 16598487.0,
    "amount": 2063000717.2,
    "code": "513050"
  },
  {
    "time": "2026-04-16 13:50:00",
    "open": 1.252,
    "high": 1.252,
    "low": 1.252,
    "close": 1.252,
    "volume": 16634572.0,
    "amount": 2067518249.2,
    "code": "513050"
  },
  {
    "time": "2026-04-16 13:51:00",
    "open": 1.252,
    "high": 1.253,
    "low": 1.252,
    "close": 1.253,
    "volume": 16690305.0,
    "amount": 2074496345.2,
    "code": "513050"
  },
  {
    "time": "2026-04-16 13:52:00",
    "open": 1.253,
    "high": 1.253,
    "low": 1.253,
    "close": 1.253,
    "volume": 16710740.0,
    "amount": 2077056662.2,
    "code": "513050"
  },
  {
    "time": "2026-04-16 13:53:00",
    "open": 1.253,
    "high": 1.253,
    "low": 1.253,
    "close": 1.253,
    "volume": 16841373.0,
    "amount": 2093425401.21,
    "code": "513050"
  },
  {
    "time": "2026-04-16 13:54:00",
    "open": 1.253,
    "high": 1.254,
    "low": 1.253,
    "close": 1.254,
    "volume": 16924580.0,
    "amount": 2103859485.21,
    "code": "513050"
  },
  {
    "time": "2026-04-16 13:55:00",
    "open": 1.254,
    "high": 1.254,
    "low": 1.254,
    "close": 1.254,
    "volume": 16956413.0,
    "amount": 2107853050.21,
    "code": "513050"
  },
  {
    "time": "2026-04-16 13:56:00",
    "open": 1.254,
    "high": 1.255,
    "low": 1.254,
    "close": 1.255,
    "volume": 16975557.0,
    "amount": 2110254288.21,
    "code": "513050"
  },
  {
    "time": "2026-04-16 13:57:00",
    "open": 1.255,
    "high": 1.255,
    "low": 1.254,
    "close": 1.254,
    "volume": 16987599.0,
    "amount": 2111764625.21,
    "code": "513050"
  },
  {
    "time": "2026-04-16 13:58:00",
    "open": 1.254,
    "high": 1.254,
    "low": 1.254,
    "close": 1.254,
    "volume": 17022535.0,
    "amount": 2116145923.21,
    "code": "513050"
  },
  {
    "time": "2026-04-16 13:59:00",
    "open": 1.254,
    "high": 1.254,
    "low": 1.254,
    "close": 1.254,
    "volume": 17107087.0,
    "amount": 2126748756.21,
    "code": "513050"
  },
  {
    "time": "2026-04-16 14:00:00",
    "open": 1.254,
    "high": 1.255,
    "low": 1.254,
    "close": 1.255,
    "volume": 17120181.0,
    "amount": 2128391362.21,
    "code": "513050"
  },
  {
    "time": "2026-04-16 14:01:00",
    "open": 1.255,
    "high": 1.255,
    "low": 1.254,
    "close": 1.254,
    "volume": 17129126.0,
    "amount": 2129513348.21,
    "code": "513050"
  },
  {
    "time": "2026-04-16 14:02:00",
    "open": 1.254,
    "high": 1.254,
    "low": 1.254,
    "close": 1.254,
    "volume": 17139420.0,
    "amount": 2130805037.22,
    "code": "513050"
  },
  {
    "time": "2026-04-16 14:03:00",
    "open": 1.254,
    "high": 1.254,
    "low": 1.254,
    "close": 1.254,
    "volume": 17159831.0,
    "amount": 2133364951.22,
    "code": "513050"
  },
  {
    "time": "2026-04-16 14:04:00",
    "open": 1.254,
    "high": 1.254,
    "low": 1.254,
    "close": 1.254,
    "volume": 17194801.0,
    "amount": 2137750612.22,
    "code": "513050"
  },
  {
    "time": "2026-04-16 14:05:00",
    "open": 1.254,
    "high": 1.254,
    "low": 1.253,
    "close": 1.253,
    "volume": 17207112.0,
    "amount": 2139293473.22,
    "code": "513050"
  },
  {
    "time": "2026-04-16 14:06:00",
    "open": 1.253,
    "high": 1.253,
    "low": 1.252,
    "close": 1.252,
    "volume": 17395766.0,
    "amount": 2162931677.22,
    "code": "513050"
  },
  {
    "time": "2026-04-16 14:07:00",
    "open": 1.252,
    "high": 1.253,
    "low": 1.252,
    "close": 1.253,
    "volume": 17479294.0,
    "amount": 2173396606.22,
    "code": "513050"
  },
  {
    "time": "2026-04-16 14:08:00",
    "open": 1.253,
    "high": 1.254,
    "low": 1.253,
    "close": 1.254,
    "volume": 17513195.0,
    "amount": 2177646610.22,
    "code": "513050"
  },
  {
    "time": "2026-04-16 14:09:00",
    "open": 1.254,
    "high": 1.255,
    "low": 1.254,
    "close": 1.255,
    "volume": 17618755.0,
    "amount": 2190883733.23,
    "code": "513050"
  },
  {
    "time": "2026-04-16 14:10:00",
    "open": 1.255,
    "high": 1.255,
    "low": 1.255,
    "close": 1.255,
    "volume": 17655005.0,
    "amount": 2195431555.23,
    "code": "513050"
  },
  {
    "time": "2026-04-16 14:11:00",
    "open": 1.255,
    "high": 1.255,
    "low": 1.254,
    "close": 1.254,
    "volume": 17677559.0,
    "amount": 2198260596.23,
    "code": "513050"
  },
  {
    "time": "2026-04-16 14:12:00",
    "open": 1.254,
    "high": 1.254,
    "low": 1.254,
    "close": 1.254,
    "volume": 17698070.0,
    "amount": 2200834230.23,
    "code": "513050"
  },
  {
    "time": "2026-04-16 14:13:00",
    "open": 1.254,
    "high": 1.254,
    "low": 1.254,
    "close": 1.254,
    "volume": 17704403.0,
    "amount": 2201628758.23,
    "code": "513050"
  },
  {
    "time": "2026-04-16 14:14:00",
    "open": 1.254,
    "high": 1.254,
    "low": 1.254,
    "close": 1.254,
    "volume": 17724260.0,
    "amount": 2204119582.23,
    "code": "513050"
  },
  {
    "time": "2026-04-16 14:15:00",
    "open": 1.254,
    "high": 1.255,
    "low": 1.254,
    "close": 1.255,
    "volume": 17755295.0,
    "amount": 2208013755.23,
    "code": "513050"
  },
  {
    "time": "2026-04-16 14:16:00",
    "open": 1.255,
    "high": 1.255,
    "low": 1.254,
    "close": 1.254,
    "volume": 17771413.0,
    "amount": 2210035376.23,
    "code": "513050"
  },
  {
    "time": "2026-04-16 14:17:00",
    "open": 1.254,
    "high": 1.254,
    "low": 1.254,
    "close": 1.254,
    "volume": 17811913.0,
    "amount": 2215114925.23,
    "code": "513050"
  },
  {
    "time": "2026-04-16 14:18:00",
    "open": 1.254,
    "high": 1.255,
    "low": 1.254,
    "close": 1.255,
    "volume": 17819979.0,
    "amount": 2216126801.23,
    "code": "513050"
  },
  {
    "time": "2026-04-16 14:19:00",
    "open": 1.255,
    "high": 1.256,
    "low": 1.255,
    "close": 1.256,
    "volume": 18028477.0,
    "amount": 2242293952.24,
    "code": "513050"
  },
  {
    "time": "2026-04-16 14:20:00",
    "open": 1.256,
    "high": 1.256,
    "low": 1.255,
    "close": 1.255,
    "volume": 18065146.0,
    "amount": 2246898537.24,
    "code": "513050"
  },
  {
    "time": "2026-04-16 14:21:00",
    "open": 1.255,
    "high": 1.256,
    "low": 1.255,
    "close": 1.256,
    "volume": 18087214.0,
    "amount": 2249669915.24,
    "code": "513050"
  },
  {
    "time": "2026-04-16 14:22:00",
    "open": 1.256,
    "high": 1.256,
    "low": 1.255,
    "close": 1.255,
    "volume": 18109092.0,
    "amount": 2252416241.24,
    "code": "513050"
  },
  {
    "time": "2026-04-16 14:23:00",
    "open": 1.255,
    "high": 1.256,
    "low": 1.255,
    "close": 1.256,
    "volume": 18123684.0,
    "amount": 2254248239.24,
    "code": "513050"
  },
  {
    "time": "2026-04-16 14:24:00",
    "open": 1.256,
    "high": 1.256,
    "low": 1.255,
    "close": 1.255,
    "volume": 18132652.0,
    "amount": 2255374101.24,
    "code": "513050"
  },
  {
    "time": "2026-04-16 14:25:00",
    "open": 1.255,
    "high": 1.256,
    "low": 1.255,
    "close": 1.256,
    "volume": 18149509.0,
    "amount": 2257490923.24,
    "code": "513050"
  },
  {
    "time": "2026-04-16 14:26:00",
    "open": 1.256,
    "high": 1.257,
    "low": 1.256,
    "close": 1.257,
    "volume": 18253217.0,
    "amount": 2270517204.24,
    "code": "513050"
  },
  {
    "time": "2026-04-16 14:27:00",
    "open": 1.257,
    "high": 1.257,
    "low": 1.257,
    "close": 1.257,
    "volume": 18282508.0,
    "amount": 2274197447.24,
    "code": "513050"
  },
  {
    "time": "2026-04-16 14:28:00",
    "open": 1.257,
    "high": 1.257,
    "low": 1.256,
    "close": 1.256,
    "volume": 18298925.0,
    "amount": 2276259929.25,
    "code": "513050"
  },
  {
    "time": "2026-04-16 14:29:00",
    "open": 1.256,
    "high": 1.256,
    "low": 1.256,
    "close": 1.256,
    "volume": 18384343.0,
    "amount": 2286988901.25,
    "code": "513050"
  },
  {
    "time": "2026-04-16 14:30:00",
    "open": 1.256,
    "high": 1.257,
    "low": 1.256,
    "close": 1.257,
    "volume": 18403513.0,
    "amount": 2289397461.25,
    "code": "513050"
  },
  {
    "time": "2026-04-16 14:31:00",
    "open": 1.257,
    "high": 1.257,
    "low": 1.257,
    "close": 1.257,
    "volume": 18466525.0,
    "amount": 2297316581.25,
    "code": "513050"
  },
  {
    "time": "2026-04-16 14:32:00",
    "open": 1.257,
    "high": 1.257,
    "low": 1.256,
    "close": 1.256,
    "volume": 18563445.0,
    "amount": 2309498635.25,
    "code": "513050"
  },
  {
    "time": "2026-04-16 14:33:00",
    "open": 1.256,
    "high": 1.257,
    "low": 1.256,
    "close": 1.257,
    "volume": 18615274.0,
    "amount": 2316013859.25,
    "code": "513050"
  },
  {
    "time": "2026-04-16 14:34:00",
    "open": 1.257,
    "high": 1.258,
    "low": 1.257,
    "close": 1.258,
    "volume": 18638780.0,
    "amount": 2318969984.25,
    "code": "513050"
  },
  {
    "time": "2026-04-16 14:35:00",
    "open": 1.258,
    "high": 1.258,
    "low": 1.258,
    "close": 1.258,
    "volume": 18743973.0,
    "amount": 2332195575.26,
    "code": "513050"
  },
  {
    "time": "2026-04-16 14:36:00",
    "open": 1.258,
    "high": 1.258,
    "low": 1.258,
    "close": 1.258,
    "volume": 18780551.0,
    "amount": 2336794407.26,
    "code": "513050"
  },
  {
    "time": "2026-04-16 14:37:00",
    "open": 1.258,
    "high": 1.258,
    "low": 1.257,
    "close": 1.257,
    "volume": 18795506.0,
    "amount": 2338675145.26,
    "code": "513050"
  },
  {
    "time": "2026-04-16 14:38:00",
    "open": 1.257,
    "high": 1.257,
    "low": 1.257,
    "close": 1.257,
    "volume": 18807781.0,
    "amount": 2340218590.26,
    "code": "513050"
  },
  {
    "time": "2026-04-16 14:39:00",
    "open": 1.257,
    "high": 1.257,
    "low": 1.257,
    "close": 1.257,
    "volume": 18818738.0,
    "amount": 2341596540.26,
    "code": "513050"
  },
  {
    "time": "2026-04-16 14:40:00",
    "open": 1.257,
    "high": 1.257,
    "low": 1.257,
    "close": 1.257,
    "volume": 18845697.0,
    "amount": 2344987374.26,
    "code": "513050"
  },
  {
    "time": "2026-04-16 14:41:00",
    "open": 1.257,
    "high": 1.257,
    "low": 1.257,
    "close": 1.257,
    "volume": 18884701.0,
    "amount": 2349892582.26,
    "code": "513050"
  },
  {
    "time": "2026-04-16 14:42:00",
    "open": 1.257,
    "high": 1.257,
    "low": 1.257,
    "close": 1.257,
    "volume": 18896063.0,
    "amount": 2351321185.26,
    "code": "513050"
  },
  {
    "time": "2026-04-16 14:43:00",
    "open": 1.257,
    "high": 1.258,
    "low": 1.257,
    "close": 1.258,
    "volume": 19053700.0,
    "amount": 2371152051.27,
    "code": "513050"
  },
  {
    "time": "2026-04-16 14:44:00",
    "open": 1.258,
    "high": 1.258,
    "low": 1.258,
    "close": 1.258,
    "volume": 19109187.0,
    "amount": 2378137453.27,
    "code": "513050"
  },
  {
    "time": "2026-04-16 14:45:00",
    "open": 1.258,
    "high": 1.26,
    "low": 1.258,
    "close": 1.26,
    "volume": 19267949.0,
    "amount": 2398125282.27,
    "code": "513050"
  },
  {
    "time": "2026-04-16 14:46:00",
    "open": 1.26,
    "high": 1.26,
    "low": 1.26,
    "close": 1.26,
    "volume": 19297652.0,
    "amount": 2401867224.27,
    "code": "513050"
  },
  {
    "time": "2026-04-16 14:47:00",
    "open": 1.26,
    "high": 1.26,
    "low": 1.26,
    "close": 1.26,
    "volume": 19474118.0,
    "amount": 2424085565.28,
    "code": "513050"
  },
  {
    "time": "2026-04-16 14:48:00",
    "open": 1.26,
    "high": 1.26,
    "low": 1.259,
    "close": 1.259,
    "volume": 19491777.0,
    "amount": 2426309856.24,
    "code": "513050"
  },
  {
    "time": "2026-04-16 14:49:00",
    "open": 1.259,
    "high": 1.26,
    "low": 1.259,
    "close": 1.26,
    "volume": 19572892.0,
    "amount": 2436522839.24,
    "code": "513050"
  },
  {
    "time": "2026-04-16 14:50:00",
    "open": 1.26,
    "high": 1.26,
    "low": 1.259,
    "close": 1.259,
    "volume": 19592059.0,
    "amount": 2438936657.24,
    "code": "513050"
  },
  {
    "time": "2026-04-16 14:51:00",
    "open": 1.259,
    "high": 1.259,
    "low": 1.259,
    "close": 1.259,
    "volume": 19722605.0,
    "amount": 2455375173.24,
    "code": "513050"
  },
  {
    "time": "2026-04-16 14:52:00",
    "open": 1.259,
    "high": 1.259,
    "low": 1.258,
    "close": 1.258,
    "volume": 19767508.0,
    "amount": 2461026883.24,
    "code": "513050"
  },
  {
    "time": "2026-04-16 14:53:00",
    "open": 1.258,
    "high": 1.258,
    "low": 1.258,
    "close": 1.258,
    "volume": 19818400.0,
    "amount": 2467430406.25,
    "code": "513050"
  },
  {
    "time": "2026-04-16 14:54:00",
    "open": 1.258,
    "high": 1.259,
    "low": 1.258,
    "close": 1.259,
    "volume": 19869731.0,
    "amount": 2473889510.25,
    "code": "513050"
  },
  {
    "time": "2026-04-16 14:55:00",
    "open": 1.259,
    "high": 1.259,
    "low": 1.257,
    "close": 1.257,
    "volume": 20009947.0,
    "amount": 2491527578.25,
    "code": "513050"
  },
  {
    "time": "2026-04-16 14:56:00",
    "open": 1.257,
    "high": 1.257,
    "low": 1.257,
    "close": 1.257,
    "volume": 20092101.0,
    "amount": 2501856340.25,
    "code": "513050"
  },
  {
    "time": "2026-04-16 14:57:00",
    "open": 1.257,
    "high": 1.257,
    "low": 1.257,
    "close": 1.257,
    "volume": 20283083.0,
    "amount": 2525851753.25,
    "code": "513050"
  },
  {
    "time": "2026-04-16 14:58:00",
    "open": 1.257,
    "high": 1.257,
    "low": 1.256,
    "close": 1.256,
    "volume": 20353677.0,
    "amount": 2534723348.25,
    "code": "513050"
  },
  {
    "time": "2026-04-16 14:59:00",
    "open": 1.256,
    "high": 1.256,
    "low": 1.256,
    "close": 1.256,
    "volume": 20427342.0,
    "amount": 2543981204.25,
    "code": "513050"
  },
  {
    "time": "2026-04-16 15:00:00",
    "open": 1.256,
    "high": 1.257,
    "low": 1.256,
    "close": 1.257,
    "volume": 20507448.0,
    "amount": 2554052573.25,
    "code": "513050"
  }
]