[
  {
    "time": "2026-04-22 09:30:00",
    "open": 2.087,
    "high": 2.087,
    "low": 2.087,
    "close": 2.087,
    "volume": 1982.0,
    "amount": 413643.0,
    "code": "513390"
  },
  {
    "time": "2026-04-22 09:31:00",
    "open": 2.087,
    "high": 2.087,
    "low": 2.083,
    "close": 2.083,
    "volume": 4103.0,
    "amount": 855409.0,
    "code": "513390"
  },
  {
    "time": "2026-04-22 09:32:00",
    "open": 2.083,
    "high": 2.083,
    "low": 2.08,
    "close": 2.08,
    "volume": 8959.0,
    "amount": 1866430.0,
    "code": "513390"
  },
  {
    "time": "2026-04-22 09:33:00",
    "open": 2.08,
    "high": 2.081,
    "low": 2.08,
    "close": 2.081,
    "volume": 12527.0,
    "amount": 2608903.0,
    "code": "513390"
  },
  {
    "time": "2026-04-22 09:34:00",
    "open": 2.081,
    "high": 2.081,
    "low": 2.08,
    "close": 2.08,
    "volume": 19535.0,
    "amount": 4066892.0,
    "code": "513390"
  },
  {
    "time": "2026-04-22 09:35:00",
    "open": 2.08,
    "high": 2.08,
    "low": 2.078,
    "close": 2.078,
    "volume": 23308.0,
    "amount": 4851249.0,
    "code": "513390"
  },
  {
    "time": "2026-04-22 09:36:00",
    "open": 2.078,
    "high": 2.079,
    "low": 2.078,
    "close": 2.079,
    "volume": 27853.0,
    "amount": 5796004.0,
    "code": "513390"
  },
  {
    "time": "2026-04-22 09:37:00",
    "open": 2.079,
    "high": 2.079,
    "low": 2.079,
    "close": 2.079,
    "volume": 33010.0,
    "amount": 6868000.0,
    "code": "513390"
  },
  {
    "time": "2026-04-22 09:38:00",
    "open": 2.079,
    "high": 2.081,
    "low": 2.079,
    "close": 2.081,
    "volume": 37074.0,
    "amount": 7713553.0,
    "code": "513390"
  },
  {
    "time": "2026-04-22 09:39:00",
    "open": 2.081,
    "high": 2.081,
    "low": 2.081,
    "close": 2.081,
    "volume": 39687.0,
    "amount": 8257356.0,
    "code": "513390"
  },
  {
    "time": "2026-04-22 09:40:00",
    "open": 2.081,
    "high": 2.082,
    "low": 2.081,
    "close": 2.082,
    "volume": 45552.0,
    "amount": 9478380.0,
    "code": "513390"
  },
  {
    "time": "2026-04-22 09:41:00",
    "open": 2.082,
    "high": 2.083,
    "low": 2.082,
    "close": 2.083,
    "volume": 47389.0,
    "amount": 9860931.0,
    "code": "513390"
  },
  {
    "time": "2026-04-22 09:42:00",
    "open": 2.083,
    "high": 2.083,
    "low": 2.082,
    "close": 2.082,
    "volume": 49766.0,
    "amount": 10356014.0,
    "code": "513390"
  },
  {
    "time": "2026-04-22 09:43:00",
    "open": 2.082,
    "high": 2.082,
    "low": 2.082,
    "close": 2.082,
    "volume": 50641.0,
    "amount": 10538250.0,
    "code": "513390"
  },
  {
    "time": "2026-04-22 09:44:00",
    "open": 2.082,
    "high": 2.082,
    "low": 2.082,
    "close": 2.082,
    "volume": 52934.0,
    "amount": 11015698.0,
    "code": "513390"
  },
  {
    "time": "2026-04-22 09:45:00",
    "open": 2.082,
    "high": 2.082,
    "low": 2.082,
    "close": 2.082,
    "volume": 53547.0,
    "amount": 11143334.0,
    "code": "513390"
  },
  {
    "time": "2026-04-22 09:46:00",
    "open": 2.082,
    "high": 2.082,
    "low": 2.082,
    "close": 2.082,
    "volume": 53605.0,
    "amount": 11155412.0,
    "code": "513390"
  },
  {
    "time": "2026-04-22 09:47:00",
    "open": 2.082,
    "high": 2.082,
    "low": 2.081,
    "close": 2.081,
    "volume": 54116.0,
    "amount": 11261785.0,
    "code": "513390"
  },
  {
    "time": "2026-04-22 09:48:00",
    "open": 2.081,
    "high": 2.081,
    "low": 2.08,
    "close": 2.08,
    "volume": 56204.0,
    "amount": 11696285.0,
    "code": "513390"
  },
  {
    "time": "2026-04-22 09:49:00",
    "open": 2.08,
    "high": 2.081,
    "low": 2.08,
    "close": 2.081,
    "volume": 57604.0,
    "amount": 11987552.0,
    "code": "513390"
  },
  {
    "time": "2026-04-22 09:50:00",
    "open": 2.081,
    "high": 2.081,
    "low": 2.081,
    "close": 2.081,
    "volume": 58286.0,
    "amount": 12129424.0,
    "code": "513390"
  },
  {
    "time": "2026-04-22 09:51:00",
    "open": 2.081,
    "high": 2.081,
    "low": 2.081,
    "close": 2.081,
    "volume": 58622.0,
    "amount": 12199345.0,
    "code": "513390"
  },
  {
    "time": "2026-04-22 09:52:00",
    "open": 2.081,
    "high": 2.081,
    "low": 2.081,
    "close": 2.081,
    "volume": 59194.0,
    "amount": 12318427.0,
    "code": "513390"
  },
  {
    "time": "2026-04-22 09:53:00",
    "open": 2.081,
    "high": 2.082,
    "low": 2.081,
    "close": 2.082,
    "volume": 59789.0,
    "amount": 12442270.0,
    "code": "513390"
  },
  {
    "time": "2026-04-22 09:54:00",
    "open": 2.082,
    "high": 2.082,
    "low": 2.081,
    "close": 2.081,
    "volume": 60027.0,
    "amount": 12491799.0,
    "code": "513390"
  },
  {
    "time": "2026-04-22 09:55:00",
    "open": 2.081,
    "high": 2.082,
    "low": 2.081,
    "close": 2.082,
    "volume": 61229.0,
    "amount": 12742046.0,
    "code": "513390"
  },
  {
    "time": "2026-04-22 09:56:00",
    "open": 2.082,
    "high": 2.082,
    "low": 2.081,
    "close": 2.081,
    "volume": 61887.0,
    "amount": 12879034.0,
    "code": "513390"
  },
  {
    "time": "2026-04-22 09:57:00",
    "open": 2.081,
    "high": 2.081,
    "low": 2.081,
    "close": 2.081,
    "volume": 62327.0,
    "amount": 12970598.0,
    "code": "513390"
  },
  {
    "time": "2026-04-22 09:58:00",
    "open": 2.081,
    "high": 2.082,
    "low": 2.081,
    "close": 2.082,
    "volume": 62744.0,
    "amount": 13057386.0,
    "code": "513390"
  },
  {
    "time": "2026-04-22 09:59:00",
    "open": 2.082,
    "high": 2.082,
    "low": 2.081,
    "close": 2.081,
    "volume": 63376.0,
    "amount": 13188925.0,
    "code": "513390"
  },
  {
    "time": "2026-04-22 10:00:00",
    "open": 2.081,
    "high": 2.081,
    "low": 2.081,
    "close": 2.081,
    "volume": 63742.0,
    "amount": 13265111.0,
    "code": "513390"
  },
  {
    "time": "2026-04-22 10:01:00",
    "open": 2.081,
    "high": 2.081,
    "low": 2.08,
    "close": 2.08,
    "volume": 64488.0,
    "amount": 13420354.0,
    "code": "513390"
  },
  {
    "time": "2026-04-22 10:02:00",
    "open": 2.08,
    "high": 2.08,
    "low": 2.08,
    "close": 2.08,
    "volume": 66557.0,
    "amount": 13850706.0,
    "code": "513390"
  },
  {
    "time": "2026-04-22 10:03:00",
    "open": 2.08,
    "high": 2.08,
    "low": 2.08,
    "close": 2.08,
    "volume": 68355.0,
    "amount": 14224772.0,
    "code": "513390"
  },
  {
    "time": "2026-04-22 10:04:00",
    "open": 2.08,
    "high": 2.081,
    "low": 2.08,
    "close": 2.081,
    "volume": 70268.0,
    "amount": 14622826.0,
    "code": "513390"
  },
  {
    "time": "2026-04-22 10:05:00",
    "open": 2.081,
    "high": 2.081,
    "low": 2.08,
    "close": 2.08,
    "volume": 72525.0,
    "amount": 15092288.0,
    "code": "513390"
  },
  {
    "time": "2026-04-22 10:06:00",
    "open": 2.08,
    "high": 2.08,
    "low": 2.079,
    "close": 2.079,
    "volume": 77513.0,
    "amount": 16129659.0,
    "code": "513390"
  },
  {
    "time": "2026-04-22 10:07:00",
    "open": 2.079,
    "high": 2.08,
    "low": 2.079,
    "close": 2.08,
    "volume": 77759.0,
    "amount": 16180824.0,
    "code": "513390"
  },
  {
    "time": "2026-04-22 10:08:00",
    "open": 2.08,
    "high": 2.081,
    "low": 2.08,
    "close": 2.081,
    "volume": 79877.0,
    "amount": 16621375.0,
    "code": "513390"
  },
  {
    "time": "2026-04-22 10:09:00",
    "open": 2.081,
    "high": 2.081,
    "low": 2.08,
    "close": 2.08,
    "volume": 80005.0,
    "amount": 16648009.0,
    "code": "513390"
  },
  {
    "time": "2026-04-22 10:10:00",
    "open": 2.08,
    "high": 2.08,
    "low": 2.08,
    "close": 2.08,
    "volume": 80669.0,
    "amount": 16786121.0,
    "code": "513390"
  },
  {
    "time": "2026-04-22 10:11:00",
    "open": 2.08,
    "high": 2.08,
    "low": 2.08,
    "close": 2.08,
    "volume": 81282.0,
    "amount": 16913635.0,
    "code": "513390"
  },
  {
    "time": "2026-04-22 10:12:00",
    "open": 2.08,
    "high": 2.08,
    "low": 2.08,
    "close": 2.08,
    "volume": 81944.0,
    "amount": 17051392.0,
    "code": "513390"
  },
  {
    "time": "2026-04-22 10:13:00",
    "open": 2.08,
    "high": 2.08,
    "low": 2.08,
    "close": 2.08,
    "volume": 82294.0,
    "amount": 17124192.0,
    "code": "513390"
  },
  {
    "time": "2026-04-22 10:14:00",
    "open": 2.08,
    "high": 2.081,
    "low": 2.08,
    "close": 2.081,
    "volume": 82309.0,
    "amount": 17127313.0,
    "code": "513390"
  },
  {
    "time": "2026-04-22 10:15:00",
    "open": 2.081,
    "high": 2.081,
    "low": 2.08,
    "close": 2.08,
    "volume": 84434.0,
    "amount": 17569313.0,
    "code": "513390"
  },
  {
    "time": "2026-04-22 10:16:00",
    "open": 2.08,
    "high": 2.08,
    "low": 2.079,
    "close": 2.079,
    "volume": 101627.0,
    "amount": 21144380.0,
    "code": "513390"
  },
  {
    "time": "2026-04-22 10:17:00",
    "open": 2.079,
    "high": 2.079,
    "low": 2.079,
    "close": 2.079,
    "volume": 101663.0,
    "amount": 21151866.0,
    "code": "513390"
  },
  {
    "time": "2026-04-22 10:18:00",
    "open": 2.079,
    "high": 2.08,
    "low": 2.079,
    "close": 2.08,
    "volume": 101683.0,
    "amount": 21156025.0,
    "code": "513390"
  },
  {
    "time": "2026-04-22 10:19:00",
    "open": 2.08,
    "high": 2.08,
    "low": 2.079,
    "close": 2.079,
    "volume": 101879.0,
    "amount": 21196773.0,
    "code": "513390"
  },
  {
    "time": "2026-04-22 10:20:00",
    "open": 2.079,
    "high": 2.08,
    "low": 2.079,
    "close": 2.08,
    "volume": 103162.0,
    "amount": 21463632.0,
    "code": "513390"
  },
  {
    "time": "2026-04-22 10:21:00",
    "open": 2.08,
    "high": 2.08,
    "low": 2.08,
    "close": 2.08,
    "volume": 104760.0,
    "amount": 21796021.0,
    "code": "513390"
  },
  {
    "time": "2026-04-22 10:22:00",
    "open": 2.08,
    "high": 2.081,
    "low": 2.08,
    "close": 2.081,
    "volume": 105235.0,
    "amount": 21894861.0,
    "code": "513390"
  },
  {
    "time": "2026-04-22 10:23:00",
    "open": 2.081,
    "high": 2.081,
    "low": 2.08,
    "close": 2.08,
    "volume": 105621.0,
    "amount": 21975188.0,
    "code": "513390"
  },
  {
    "time": "2026-04-22 10:24:00",
    "open": 2.08,
    "high": 2.08,
    "low": 2.08,
    "close": 2.08,
    "volume": 105806.0,
    "amount": 22013676.0,
    "code": "513390"
  },
  {
    "time": "2026-04-22 10:25:00",
    "open": 2.08,
    "high": 2.08,
    "low": 2.08,
    "close": 2.08,
    "volume": 106221.0,
    "amount": 22100000.0,
    "code": "513390"
  },
  {
    "time": "2026-04-22 10:26:00",
    "open": 2.08,
    "high": 2.08,
    "low": 2.08,
    "close": 2.08,
    "volume": 108041.0,
    "amount": 22478560.0,
    "code": "513390"
  },
  {
    "time": "2026-04-22 10:27:00",
    "open": 2.08,
    "high": 2.08,
    "low": 2.08,
    "close": 2.08,
    "volume": 110059.0,
    "amount": 22898302.0,
    "code": "513390"
  },
  {
    "time": "2026-04-22 10:28:00",
    "open": 2.08,
    "high": 2.08,
    "low": 2.08,
    "close": 2.08,
    "volume": 111421.0,
    "amount": 23181598.0,
    "code": "513390"
  },
  {
    "time": "2026-04-22 10:29:00",
    "open": 2.08,
    "high": 2.08,
    "low": 2.08,
    "close": 2.08,
    "volume": 112059.0,
    "amount": 23314302.0,
    "code": "513390"
  },
  {
    "time": "2026-04-22 10:30:00",
    "open": 2.08,
    "high": 2.08,
    "low": 2.08,
    "close": 2.08,
    "volume": 112059.0,
    "amount": 23314302.0,
    "code": "513390"
  },
  {
    "time": "2026-04-22 10:31:00",
    "open": 2.08,
    "high": 2.081,
    "low": 2.08,
    "close": 2.081,
    "volume": 114146.0,
    "amount": 23748407.0,
    "code": "513390"
  },
  {
    "time": "2026-04-22 10:32:00",
    "open": 2.081,
    "high": 2.081,
    "low": 2.081,
    "close": 2.081,
    "volume": 114851.0,
    "amount": 23895048.0,
    "code": "513390"
  },
  {
    "time": "2026-04-22 10:33:00",
    "open": 2.081,
    "high": 2.081,
    "low": 2.081,
    "close": 2.081,
    "volume": 121600.0,
    "amount": 25299506.0,
    "code": "513390"
  },
  {
    "time": "2026-04-22 10:34:00",
    "open": 2.081,
    "high": 2.081,
    "low": 2.081,
    "close": 2.081,
    "volume": 122230.0,
    "amount": 25430546.0,
    "code": "513390"
  },
  {
    "time": "2026-04-22 10:35:00",
    "open": 2.081,
    "high": 2.081,
    "low": 2.08,
    "close": 2.08,
    "volume": 123514.0,
    "amount": 25697621.0,
    "code": "513390"
  },
  {
    "time": "2026-04-22 10:36:00",
    "open": 2.08,
    "high": 2.08,
    "low": 2.08,
    "close": 2.08,
    "volume": 123699.0,
    "amount": 25736101.0,
    "code": "513390"
  },
  {
    "time": "2026-04-22 10:37:00",
    "open": 2.08,
    "high": 2.08,
    "low": 2.08,
    "close": 2.08,
    "volume": 123746.0,
    "amount": 25745877.0,
    "code": "513390"
  },
  {
    "time": "2026-04-22 10:38:00",
    "open": 2.08,
    "high": 2.08,
    "low": 2.079,
    "close": 2.079,
    "volume": 123751.0,
    "amount": 25746916.0,
    "code": "513390"
  },
  {
    "time": "2026-04-22 10:39:00",
    "open": 2.079,
    "high": 2.08,
    "low": 2.079,
    "close": 2.08,
    "volume": 124043.0,
    "amount": 25807652.0,
    "code": "513390"
  },
  {
    "time": "2026-04-22 10:40:00",
    "open": 2.08,
    "high": 2.08,
    "low": 2.08,
    "close": 2.08,
    "volume": 125898.0,
    "amount": 26193492.0,
    "code": "513390"
  },
  {
    "time": "2026-04-22 10:41:00",
    "open": 2.08,
    "high": 2.081,
    "low": 2.08,
    "close": 2.081,
    "volume": 126352.0,
    "amount": 26287947.0,
    "code": "513390"
  },
  {
    "time": "2026-04-22 10:42:00",
    "open": 2.081,
    "high": 2.081,
    "low": 2.08,
    "close": 2.08,
    "volume": 126594.0,
    "amount": 26338284.0,
    "code": "513390"
  },
  {
    "time": "2026-04-22 10:43:00",
    "open": 2.08,
    "high": 2.08,
    "low": 2.08,
    "close": 2.08,
    "volume": 126613.0,
    "amount": 26342236.0,
    "code": "513390"
  },
  {
    "time": "2026-04-22 10:44:00",
    "open": 2.08,
    "high": 2.08,
    "low": 2.08,
    "close": 2.08,
    "volume": 126714.0,
    "amount": 26363244.0,
    "code": "513390"
  },
  {
    "time": "2026-04-22 10:45:00",
    "open": 2.08,
    "high": 2.081,
    "low": 2.08,
    "close": 2.081,
    "volume": 126853.0,
    "amount": 26392156.0,
    "code": "513390"
  },
  {
    "time": "2026-04-22 10:46:00",
    "open": 2.081,
    "high": 2.081,
    "low": 2.081,
    "close": 2.081,
    "volume": 126929.0,
    "amount": 26407971.0,
    "code": "513390"
  },
  {
    "time": "2026-04-22 10:47:00",
    "open": 2.081,
    "high": 2.081,
    "low": 2.081,
    "close": 2.081,
    "volume": 126984.0,
    "amount": 26419412.0,
    "code": "513390"
  },
  {
    "time": "2026-04-22 10:48:00",
    "open": 2.081,
    "high": 2.081,
    "low": 2.081,
    "close": 2.081,
    "volume": 127001.0,
    "amount": 26422949.0,
    "code": "513390"
  },
  {
    "time": "2026-04-22 10:49:00",
    "open": 2.081,
    "high": 2.081,
    "low": 2.081,
    "close": 2.081,
    "volume": 127031.0,
    "amount": 26429192.0,
    "code": "513390"
  },
  {
    "time": "2026-04-22 10:50:00",
    "open": 2.081,
    "high": 2.081,
    "low": 2.08,
    "close": 2.08,
    "volume": 127046.0,
    "amount": 26432313.0,
    "code": "513390"
  },
  {
    "time": "2026-04-22 10:51:00",
    "open": 2.08,
    "high": 2.081,
    "low": 2.08,
    "close": 2.081,
    "volume": 127070.0,
    "amount": 26437308.0,
    "code": "513390"
  },
  {
    "time": "2026-04-22 10:52:00",
    "open": 2.081,
    "high": 2.081,
    "low": 2.08,
    "close": 2.08,
    "volume": 127126.0,
    "amount": 26448956.0,
    "code": "513390"
  },
  {
    "time": "2026-04-22 10:53:00",
    "open": 2.08,
    "high": 2.081,
    "low": 2.08,
    "close": 2.081,
    "volume": 127136.0,
    "amount": 26451037.0,
    "code": "513390"
  },
  {
    "time": "2026-04-22 10:54:00",
    "open": 2.081,
    "high": 2.081,
    "low": 2.081,
    "close": 2.081,
    "volume": 127138.0,
    "amount": 26451453.0,
    "code": "513390"
  },
  {
    "time": "2026-04-22 10:55:00",
    "open": 2.081,
    "high": 2.081,
    "low": 2.081,
    "close": 2.081,
    "volume": 127450.0,
    "amount": 26516355.0,
    "code": "513390"
  },
  {
    "time": "2026-04-22 10:56:00",
    "open": 2.081,
    "high": 2.081,
    "low": 2.081,
    "close": 2.081,
    "volume": 127807.0,
    "amount": 26590647.0,
    "code": "513390"
  },
  {
    "time": "2026-04-22 10:57:00",
    "open": 2.081,
    "high": 2.081,
    "low": 2.081,
    "close": 2.081,
    "volume": 128048.0,
    "amount": 26640799.0,
    "code": "513390"
  },
  {
    "time": "2026-04-22 10:58:00",
    "open": 2.081,
    "high": 2.081,
    "low": 2.08,
    "close": 2.08,
    "volume": 128347.0,
    "amount": 26702996.0,
    "code": "513390"
  },
  {
    "time": "2026-04-22 10:59:00",
    "open": 2.08,
    "high": 2.081,
    "low": 2.08,
    "close": 2.081,
    "volume": 128816.0,
    "amount": 26800591.0,
    "code": "513390"
  },
  {
    "time": "2026-04-22 11:00:00",
    "open": 2.081,
    "high": 2.081,
    "low": 2.08,
    "close": 2.08,
    "volume": 128826.0,
    "amount": 26802671.0,
    "code": "513390"
  },
  {
    "time": "2026-04-22 11:01:00",
    "open": 2.08,
    "high": 2.08,
    "low": 2.08,
    "close": 2.08,
    "volume": 130356.0,
    "amount": 27120912.0,
    "code": "513390"
  },
  {
    "time": "2026-04-22 11:02:00",
    "open": 2.08,
    "high": 2.081,
    "low": 2.08,
    "close": 2.081,
    "volume": 130452.0,
    "amount": 27140890.0,
    "code": "513390"
  },
  {
    "time": "2026-04-22 11:03:00",
    "open": 2.081,
    "high": 2.081,
    "low": 2.081,
    "close": 2.081,
    "volume": 131742.0,
    "amount": 27409217.0,
    "code": "513390"
  },
  {
    "time": "2026-04-22 11:04:00",
    "open": 2.081,
    "high": 2.081,
    "low": 2.08,
    "close": 2.08,
    "volume": 131782.0,
    "amount": 27417539.0,
    "code": "513390"
  },
  {
    "time": "2026-04-22 11:05:00",
    "open": 2.08,
    "high": 2.08,
    "low": 2.08,
    "close": 2.08,
    "volume": 131949.0,
    "amount": 27452287.0,
    "code": "513390"
  },
  {
    "time": "2026-04-22 11:06:00",
    "open": 2.08,
    "high": 2.082,
    "low": 2.08,
    "close": 2.082,
    "volume": 138728.0,
    "amount": 28863130.0,
    "code": "513390"
  },
  {
    "time": "2026-04-22 11:07:00",
    "open": 2.082,
    "high": 2.082,
    "low": 2.082,
    "close": 2.082,
    "volume": 141499.0,
    "amount": 29440052.0,
    "code": "513390"
  },
  {
    "time": "2026-04-22 11:08:00",
    "open": 2.082,
    "high": 2.082,
    "low": 2.082,
    "close": 2.082,
    "volume": 141548.0,
    "amount": 29450254.0,
    "code": "513390"
  },
  {
    "time": "2026-04-22 11:09:00",
    "open": 2.082,
    "high": 2.082,
    "low": 2.082,
    "close": 2.082,
    "volume": 142183.0,
    "amount": 29582461.0,
    "code": "513390"
  },
  {
    "time": "2026-04-22 11:10:00",
    "open": 2.082,
    "high": 2.082,
    "low": 2.081,
    "close": 2.081,
    "volume": 142356.0,
    "amount": 29618470.0,
    "code": "513390"
  },
  {
    "time": "2026-04-22 11:11:00",
    "open": 2.081,
    "high": 2.082,
    "low": 2.081,
    "close": 2.082,
    "volume": 142553.0,
    "amount": 29659485.0,
    "code": "513390"
  },
  {
    "time": "2026-04-22 11:12:00",
    "open": 2.082,
    "high": 2.082,
    "low": 2.081,
    "close": 2.081,
    "volume": 142642.0,
    "amount": 29678006.0,
    "code": "513390"
  },
  {
    "time": "2026-04-22 11:13:00",
    "open": 2.081,
    "high": 2.081,
    "low": 2.081,
    "close": 2.081,
    "volume": 142645.0,
    "amount": 29678630.0,
    "code": "513390"
  },
  {
    "time": "2026-04-22 11:14:00",
    "open": 2.081,
    "high": 2.081,
    "low": 2.081,
    "close": 2.081,
    "volume": 143867.0,
    "amount": 29932979.0,
    "code": "513390"
  },
  {
    "time": "2026-04-22 11:15:00",
    "open": 2.081,
    "high": 2.081,
    "low": 2.081,
    "close": 2.081,
    "volume": 144070.0,
    "amount": 29975223.0,
    "code": "513390"
  },
  {
    "time": "2026-04-22 11:16:00",
    "open": 2.081,
    "high": 2.081,
    "low": 2.081,
    "close": 2.081,
    "volume": 144172.0,
    "amount": 29996451.0,
    "code": "513390"
  },
  {
    "time": "2026-04-22 11:17:00",
    "open": 2.081,
    "high": 2.082,
    "low": 2.081,
    "close": 2.082,
    "volume": 144684.0,
    "amount": 30103048.0,
    "code": "513390"
  },
  {
    "time": "2026-04-22 11:18:00",
    "open": 2.082,
    "high": 2.082,
    "low": 2.082,
    "close": 2.082,
    "volume": 144731.0,
    "amount": 30112834.0,
    "code": "513390"
  },
  {
    "time": "2026-04-22 11:19:00",
    "open": 2.082,
    "high": 2.082,
    "low": 2.082,
    "close": 2.082,
    "volume": 146123.0,
    "amount": 30402515.0,
    "code": "513390"
  },
  {
    "time": "2026-04-22 11:20:00",
    "open": 2.082,
    "high": 2.082,
    "low": 2.081,
    "close": 2.081,
    "volume": 146409.0,
    "amount": 30462032.0,
    "code": "513390"
  },
  {
    "time": "2026-04-22 11:21:00",
    "open": 2.081,
    "high": 2.081,
    "low": 2.081,
    "close": 2.081,
    "volume": 146470.0,
    "amount": 30474728.0,
    "code": "513390"
  },
  {
    "time": "2026-04-22 11:22:00",
    "open": 2.081,
    "high": 2.081,
    "low": 2.081,
    "close": 2.081,
    "volume": 146481.0,
    "amount": 30477017.0,
    "code": "513390"
  },
  {
    "time": "2026-04-22 11:23:00",
    "open": 2.081,
    "high": 2.082,
    "low": 2.081,
    "close": 2.082,
    "volume": 146537.0,
    "amount": 30488677.0,
    "code": "513390"
  },
  {
    "time": "2026-04-22 11:24:00",
    "open": 2.082,
    "high": 2.082,
    "low": 2.082,
    "close": 2.082,
    "volume": 146704.0,
    "amount": 30523446.0,
    "code": "513390"
  },
  {
    "time": "2026-04-22 11:25:00",
    "open": 2.082,
    "high": 2.082,
    "low": 2.081,
    "close": 2.081,
    "volume": 152355.0,
    "amount": 31699467.0,
    "code": "513390"
  },
  {
    "time": "2026-04-22 11:26:00",
    "open": 2.081,
    "high": 2.082,
    "low": 2.081,
    "close": 2.082,
    "volume": 152514.0,
    "amount": 31732558.0,
    "code": "513390"
  },
  {
    "time": "2026-04-22 11:27:00",
    "open": 2.082,
    "high": 2.082,
    "low": 2.082,
    "close": 2.082,
    "volume": 153858.0,
    "amount": 32012249.0,
    "code": "513390"
  },
  {
    "time": "2026-04-22 11:28:00",
    "open": 2.082,
    "high": 2.082,
    "low": 2.082,
    "close": 2.082,
    "volume": 153858.0,
    "amount": 32012249.0,
    "code": "513390"
  },
  {
    "time": "2026-04-22 11:29:00",
    "open": 2.082,
    "high": 2.082,
    "low": 2.082,
    "close": 2.082,
    "volume": 154526.0,
    "amount": 32151267.0,
    "code": "513390"
  },
  {
    "time": "2026-04-22 11:30:00",
    "open": 2.082,
    "high": 2.082,
    "low": 2.082,
    "close": 2.082,
    "volume": 154526.0,
    "amount": 32151267.0,
    "code": "513390"
  }
]